mindaffectBCI/MindAffect_Logo.png
mindaffectBCI/__init__.py
mindaffectBCI/debug.json
mindaffectBCI/fake_recogniser.json
mindaffectBCI/mgold_61_6521_psk_60hz.png
mindaffectBCI/mgold_61_6521_psk_60hz.txt
mindaffectBCI/mgold_65_6532_psk_60hz.png
mindaffectBCI/mgold_65_6532_psk_60hz.txt
mindaffectBCI/noisetag.py
mindaffectBCI/noisetag_3x3.json
mindaffectBCI/noisetag_bci.json
mindaffectBCI/online_bci.json
mindaffectBCI/online_bci.py
mindaffectBCI/raspberry_pi_gpio.json
mindaffectBCI/rc5x5.png
mindaffectBCI/rc5x5.txt
mindaffectBCI/rc5x5_bci.json
mindaffectBCI/ssdpDiscover.py
mindaffectBCI/ssvep.png
mindaffectBCI/ssvep.txt
mindaffectBCI/ssvep_bci.json
mindaffectBCI/stimseq.py
mindaffectBCI/trigger_check.json
mindaffectBCI/utopia2output.py
mindaffectBCI/utopiaController.py
mindaffectBCI/utopiaclient.py
mindaffectBCI/decoder/FileProxyHub.py
mindaffectBCI/decoder/UtopiaDataInterface.py
mindaffectBCI/decoder/__init__.py
mindaffectBCI/decoder/analyse_datasets.py
"mindaffectBCI/decoder/butter_stopband((0, 5), (25, -1))_fs200.pk"
mindaffectBCI/decoder/ccaViewer.py
mindaffectBCI/decoder/dataset debugging.py
mindaffectBCI/decoder/datasets.py
mindaffectBCI/decoder/dec_test.py
mindaffectBCI/decoder/decoder.py
mindaffectBCI/decoder/decodingCurveSupervised.py
mindaffectBCI/decoder/decodingSupervised.py
mindaffectBCI/decoder/devent2stimsequence.py
mindaffectBCI/decoder/erpViewer.py
mindaffectBCI/decoder/linear_trend_tracker.py
mindaffectBCI/decoder/lower_bound_tracker.py
mindaffectBCI/decoder/model_fitting.py
mindaffectBCI/decoder/multipleCCA.py
mindaffectBCI/decoder/multipleMCCA.py
mindaffectBCI/decoder/normalizeOutputScores.py
mindaffectBCI/decoder/normalizeOutputScores_streamed.py
mindaffectBCI/decoder/offline_analysis.py
mindaffectBCI/decoder/preprocess.py
mindaffectBCI/decoder/readCapInf.py
mindaffectBCI/decoder/scoreOutput.py
mindaffectBCI/decoder/scoreStimulus.py
mindaffectBCI/decoder/sigViewer.py
mindaffectBCI-0.9.24.dist-info/DESCRIPTION.rst
mindaffectBCI-0.9.24.dist-info/METADATA
mindaffectBCI-0.9.24.dist-info/RECORD
mindaffectBCI-0.9.24.dist-info/WHEEL
mindaffectBCI-0.9.24.dist-info/metadata.json
mindaffectBCI-0.9.24.dist-info/top_level.txt
