Metadata-Version: 2.0
Name: mindaffectBCI
Version: 0.9.24
Summary: The MindAffect BCI python SDK
Home-page: http://github.com/mindaffect/pymindaffectBCI
Author: Jason Farquhar
Author-email: jason@mindaffect.nl
License: MIT
Platform: UNKNOWN
Classifier: Programming Language :: Python :: 3
Classifier: License :: OSI Approved :: MIT License
Classifier: Operating System :: OS Independent
Requires-Python: >=3.5
Requires-Dist: numpy (>=1.0.2)
Requires-Dist: pyglet (>=1.2)
Requires-Dist: scipy (>=1.0)
Requires-Dist: brainflow (>=3.0)
Requires-Dist: matplotlib (>=3.0)
